{
  "games": [
    {
      "id": 1,
      "username": "KrishnaD",
      "score": 3,
      "amount": "6",
      "category": "21",
      "difficulty": "medium",
      "type": "boolean"
    },
    {
      "id": 2,
      "username": "KrishedNan",
      "score": 4,
      "amount": "5",
      "category": "21",
      "difficulty": "medium",
      "type": "boolean"
    },
    {
      "id": 3,
      "username": "nims",
      "score": 2,
      "amount": "4",
      "category": "9",
      "difficulty": "easy",
      "type": "multiple",
      "datetime": "2024-06-27T11:10:46.554Z"
    },
    {
      "id": 4,
      "username": "nims",
      "score": 1,
      "amount": "3",
      "category": "9",
      "difficulty": "easy",
      "type": "multiple",
      "datetime": "2024-06-27T11:15:02.079Z"
    },
    {
      "id": 5,
      "username": "nims",
      "score": 0,
      "amount": "2",
      "category": "21",
      "difficulty": "hard",
      "type": "multiple",
      "datetime": "2024-06-27T11:33:35.449Z"
    },
    {
      "id": 6,
      "username": "nims",
      "score": 0,
      "amount": "2",
      "category": "9",
      "difficulty": "easy",
      "type": "multiple",
      "datetime": "2024-06-27T11:47:16.396Z"
    },
    {
      "id": 7,
      "username": "nims",
      "score": 1,
      "amount": "3",
      "category": "9",
      "difficulty": "easy",
      "type": "multiple",
      "datetime": "2024-06-27T11:48:02.784Z"
    },
    {
      "id": 8,
      "username": "nims",
      "score": 0,
      "amount": "3",
      "category": "9",
      "difficulty": "easy",
      "type": "multiple",
      "datetime": "2024-06-27T12:04:56.134Z"
    },
    {
      "id": 9,
      "username": "nims",
      "score": 1,
      "amount": "3",
      "category": "9",
      "difficulty": "easy",
      "type": "multiple",
      "datetime": "2024-06-27T12:38:57.481Z"
    },
    {
      "id": 10,
      "username": "nims",
      "score": 0,
      "amount": "3",
      "category": "9",
      "difficulty": "easy",
      "type": "multiple",
      "datetime": "2024-06-27T12:45:42.207Z"
    },
    {
      "id": 11,
      "username": "nims",
      "score": 1,
      "amount": "3",
      "category": "9",
      "difficulty": "easy",
      "type": "multiple",
      "datetime": "2024-06-27T12:45:53.295Z"
    },
    {
      "id": 12,
      "username": "Guest",
      "score": 3,
      "amount": 3,
      "category": "Entertainment: Film",
      "difficulty": "medium",
      "type": "multiple",
      "datetime": "2024-06-27T12:52:12.607Z"
    },
    {
      "id": 13,
      "username": "Guest",
      "score": 2,
      "amount": 3,
      "category": "Entertainment: Japanese Anime &amp; Manga",
      "difficulty": "medium",
      "type": "multiple",
      "datetime": "2024-06-27T12:53:11.266Z"
    },
    {
      "id": 14,
      "username": "Guest",
      "score": 3,
      "amount": 8,
      "category": "General Knowledge",
      "difficulty": "medium",
      "type": "multiple",
      "datetime": "2024-06-27T12:53:28.580Z"
    },
    {
      "id": 15,
      "username": "nims",
      "score": 1,
      "amount": "4",
      "category": "9",
      "difficulty": "easy",
      "type": "multiple",
      "datetime": "2024-06-27T13:07:51.474Z"
    },
    {
      "id": 16,
      "username": "nims",
      "score": 0,
      "amount": "1",
      "category": "9",
      "difficulty": "easy",
      "type": "multiple",
      "datetime": "2024-06-27T13:08:08.518Z"
    },
    {
      "id": 17,
      "username": "nims",
      "score": 1,
      "amount": "3",
      "category": "",
      "difficulty": "",
      "type": "multiple",
      "datetime": "2024-06-27T13:16:10.037Z"
    },
    {
      "id": 18,
      "username": "nims",
      "score": 2,
      "amount": "5",
      "category": "",
      "difficulty": "",
      "type": "",
      "datetime": "2024-06-27T13:16:59.548Z"
    },
    {
      "id": 19,
      "username": "nims",
      "score": 2,
      "amount": "8",
      "category": "13",
      "difficulty": "",
      "type": "",
      "datetime": "2024-06-27T13:17:21.830Z"
    },
    {
      "id": 20,
      "username": "nims",
      "score": 0,
      "amount": "4",
      "category": "",
      "difficulty": "",
      "type": "",
      "datetime": "2024-06-27T13:19:23.043Z"
    },
    {
      "id": 21,
      "username": "nims",
      "score": 0,
      "amount": "1",
      "category": "",
      "difficulty": "",
      "type": "",
      "datetime": "2024-06-27T13:19:30.085Z"
    },
    {
      "id": 22,
      "username": "nims",
      "score": 1,
      "amount": "3",
      "category": "",
      "difficulty": "",
      "type": "",
      "datetime": "2024-06-27T13:21:21.720Z"
    },
    {
      "id": 23,
      "username": "nims",
      "score": 1,
      "amount": "1",
      "category": "",
      "difficulty": "",
      "type": "",
      "datetime": "2024-06-27T13:22:01.580Z"
    },
    {
      "id": 24,
      "username": "nims",
      "score": 0,
      "amount": "1",
      "category": "",
      "difficulty": "",
      "type": "",
      "datetime": "2024-06-27T14:45:53.713Z"
    },
    {
      "id": 25,
      "username": "nims",
      "score": 5,
      "amount": "12",
      "category": "",
      "difficulty": "easy",
      "type": "boolean",
      "datetime": "2024-06-27T14:46:54.722Z"
    }
  ]
}